menustat/__init__.py
menustat/collecteddf.py
menustat/core.py
menustat/exceptions.py
menustat/log.py
menustat/orm.py
menustat/scraper.py
menustat/settings.py
menustat/utils.py
templates/menustat_config.yaml
menustat_pkg-0.0.12.dist-info/LICENSE
menustat_pkg-0.0.12.dist-info/METADATA
menustat_pkg-0.0.12.dist-info/WHEEL
menustat_pkg-0.0.12.dist-info/top_level.txt
menustat_pkg-0.0.12.dist-info/RECORD
