Metadata-Version: 2.1
Name: menustat-pkg
Version: 0.0.12
Author: Claire Peters
Author-email: clairepeters@g.harvard.edu
License: BSD License
Requires-Python: >=3.8
License-File: LICENSE
Requires-Dist: beautifulsoup4 (==4.9.3)
Requires-Dist: camelot-py[base] (==0.9.0)
Requires-Dist: chromedriver-binary-auto
Requires-Dist: ghostscript
Requires-Dist: html5lib (==1.1)
Requires-Dist: lxml (==4.6.2)
Requires-Dist: oauthlib (==3.1.1)
Requires-Dist: opencv-python
Requires-Dist: pandas (==1.3.2)
Requires-Dist: python-levenshtein (==0.12.2)
Requires-Dist: pyyaml (==5.4.1)
Requires-Dist: rapidfuzz (==1.7.1)
Requires-Dist: requests
Requires-Dist: selenium (==3.141.0)
Requires-Dist: sqlalchemy (==1.4.22)
Requires-Dist: tqdm (==4.62.1)
Requires-Dist: urllib3 (==1.26.6)
